vt_kvd/__init__.py
vt_kvd/__main__.py
vt_kvd/theme.py
vt_kvd/utils.py
vt_kvd/version.py
vt_kvd/fonts/JetBrainsMono-Thin.ttf
vt_kvd/icons/kvd-128.ico
vt_kvd/icons/kvd-256.ico
vt_kvd-0.5.0.dist-info/LICENSE
vt_kvd-0.5.0.dist-info/METADATA
vt_kvd-0.5.0.dist-info/WHEEL
vt_kvd-0.5.0.dist-info/entry_points.txt
vt_kvd-0.5.0.dist-info/top_level.txt
vt_kvd-0.5.0.dist-info/RECORD
