Metadata-Version: 2.1
Name: vt-kvd
Version: 0.5.0
Summary: A VirusTotal GUI client
Home-page: https://github.com/retifrav/vt-kvd
Author: retif
Project-URL: Bug Tracker, https://github.com/retifrav/vt-kvd/issues
Project-URL: Changelog, https://github.com/retifrav/vt-kvd/blob/master/changelog.md
Keywords: virustotal,gui
Classifier: Programming Language :: Python :: 3.8
Classifier: License :: OSI Approved :: GNU General Public License v3 (GPLv3)
Classifier: Operating System :: MacOS
Classifier: Operating System :: Microsoft :: Windows
Classifier: Operating System :: POSIX :: Linux
Classifier: Topic :: Desktop Environment
Classifier: Topic :: Software Development :: User Interfaces
Classifier: Topic :: Security
Requires-Python: >=3.8
License-File: LICENSE
Requires-Dist: dearpygui (>=1.6.0)
Requires-Dist: pandas
Requires-Dist: python-magic
Requires-Dist: vt-py
